{
  "command.Addbnddire.title": "Aggiungi voce Binding Directory",
  "command.ChgDtaara.title": "Modifica Data Area",
  "command.chgUsrspc.title": "Modifica User Space",
  "command.clearDataQueue.title": "Svuota Data Queue",
  "command.clearMessageQueue.title": "Svuota Message Queue",
  "command.clearSavf.title": "Svuota Save File",
  "command.ClrJobq.title": "Svuota Job Queue",
  "command.ClrOutq.title": "Svuota Output Queue",
  "command.DelOldSpool.title": "Elimina spool vecchi",
  "command.downloadSavf.title": "Scarica Save File",
  "command.DspJrn.title": "Interroga Journal",
  "command.EndSbs.title": "Termina Subsystem",
  "command.GenJrnRcv.title": "Genera nuovo Journal Receiver",
  "command.HldJobq.title": "Holda Job Queue",
  "command.HldOutq.title": "Holda Output Queue",
  "command.MngWtr.title": "Gestisci Writer",
  "command.QueryFile.title": "Interroga file",
  "command.restore.title": "Ripristina da Save File",
  "command.RlsJobq.title": "Rilascia Job Queue",
  "command.RlsOutq.title": "Rilascia Output Queue",
  "command.savf.title": "Salva in Save File",
  "command.sendToDataQueue.title": "Invia dati a Data Queue",
  "command.StrSbs.title": "Avvia Subsystem",
  "command.uploadSavf.title": "Carica Save File",
  "description": "Browser del file system per IBM i QSYS",
  "displayName": "IBM i FileSystem"
}